giticket/__init__.py
giticket/giticket.py
giticket-0.1.5.dist-info/AUTHORS.rst
giticket-0.1.5.dist-info/LICENSE
giticket-0.1.5.dist-info/METADATA
giticket-0.1.5.dist-info/WHEEL
giticket-0.1.5.dist-info/entry_points.txt
giticket-0.1.5.dist-info/top_level.txt
giticket-0.1.5.dist-info/RECORD
