Metadata-Version: 2.1
Name: giticket
Version: 0.1.5
Summary: Auto add ticket info to your git commits.
Home-page: https://github.com/milin/giticket
Author: Milind Shakya
Author-email: sh.milind@gmail.com
License: MIT license
Keywords: giticket
Platform: UNKNOWN
Classifier: Development Status :: 2 - Pre-Alpha
Classifier: Intended Audience :: Developers
Classifier: License :: OSI Approved :: MIT License
Classifier: Natural Language :: English
Classifier: Programming Language :: Python :: 2
Classifier: Programming Language :: Python :: 2.7
Classifier: Programming Language :: Python :: 3
Classifier: Programming Language :: Python :: 3.4
Classifier: Programming Language :: Python :: 3.5
Classifier: Programming Language :: Python :: 3.6
Classifier: Programming Language :: Python :: 3.7
Requires-Dist: pre-commit
Requires-Dist: six
